icinga_passify_bareos-0.1.4.dist-info/licenses/LICENSE
passify_bareos/__init__.py
passify_bareos/passify_bareos.py
icinga_passify_bareos-0.1.4.dist-info/METADATA
icinga_passify_bareos-0.1.4.dist-info/WHEEL
icinga_passify_bareos-0.1.4.dist-info/entry_points.txt
icinga_passify_bareos-0.1.4.dist-info/top_level.txt
icinga_passify_bareos-0.1.4.dist-info/RECORD
