Metadata-Version: 2.4
Name: icinga-passify-bareos
Version: 0.1.4
Summary: Transform Bacula / Bareos job results into an Icinga2 API passive check result. This is designed to be used with a RunScript after the job has completed on the agent.
Author-email: Bona Fide IT GmbH <github@bona-fide.it>, Olaf Rühenbeck <oruehenbeck@bona-fide.it>
License: MIT License
Project-URL: Homepage, https://github.com/BonaFideIT/passify-bareos
Keywords: icinga,api,passive,check_command
Classifier: License :: OSI Approved :: MIT License
Classifier: Programming Language :: Python
Classifier: Programming Language :: Python :: 3
Requires-Python: >=3.6
License-File: LICENSE
Provides-Extra: dev
Requires-Dist: pipenv; extra == "dev"
Requires-Dist: black; extra == "dev"
Requires-Dist: ruff; extra == "dev"
Requires-Dist: pre-commit; extra == "dev"
Dynamic: license-file
